cortesh/__init__.py
cortesh/brain/logic/base.py
cortesh/brain/logic/folder_project.py
cortesh/brain/memory/memory.py
cortesh/brain/output/command.py
cortesh/brain/output/create_file.py
cortesh/brain/output/error.py
cortesh/brain/output/message.py
cortesh/brain/output/output.py
cortesh/brain/process.py
cortesh/brain/sense/command_response.py
cortesh/brain/sense/file_content.py
cortesh/brain/sense/folder_structure.py
cortesh/brain/sense/sense.py
cortesh/cli.py
cortesh/interface/logger.py
cortesh-0.1.0.dist-info/LICENSE
cortesh-0.1.0.dist-info/METADATA
cortesh-0.1.0.dist-info/WHEEL
cortesh-0.1.0.dist-info/entry_points.txt
cortesh-0.1.0.dist-info/RECORD
