Metadata-Version: 2.1
Name: cortesh
Version: 0.1.0
Summary: Your AI Pair programmer.
Home-page: https://github.com/zeopix/cortesh
License: MIT
Author: Iván Guillén
Author-email: hello@ivanguillen.me
Requires-Python: >=3.9,<4.0
Classifier: License :: OSI Approved :: MIT License
Classifier: Programming Language :: Python :: 3
Classifier: Programming Language :: Python :: 3.9
Classifier: Programming Language :: Python :: 3.10
Classifier: Programming Language :: Python :: 3.11
Classifier: Programming Language :: Python :: 3.12
Requires-Dist: langchain (>=0.3.0,<0.4.0)
Requires-Dist: langchain-openai (>=0.2.0,<0.3.0)
Requires-Dist: numpy (>=1.21.0,<2.0.0)
Requires-Dist: python-dotenv (>=1.0.1,<2.0.0)
Requires-Dist: requests (==2.28.1)
